[
  {
    "name": "get_billing_transaction_info",
    "url": "https://open.shopee.com/documents/v2/v2.payment.get_billing_transaction_info?module=97&type=1",
    "title": "Documentation - Shopee Open Platform"
  },
  {
    "name": "get_escrow_detail",
    "url": "https://open.shopee.com/documents/v2/v2.payment.get_escrow_detail?module=97&type=1",
    "title": "Documentation - Shopee Open Platform"
  },
  {
    "name": "get_escrow_detail_batch",
    "url": "https://open.shopee.com/documents/v2/v2.payment.get_escrow_detail_batch?module=97&type=1",
    "title": "Documentation - Shopee Open Platform"
  },
  {
    "name": "get_escrow_list",
    "url": "https://open.shopee.com/documents/v2/v2.payment.get_escrow_list?module=97&type=1",
    "title": "Documentation - Shopee Open Platform"
  },
  {
    "name": "get_income_detail",
    "url": "https://open.shopee.com/documents/v2/v2.payment.get_income_detail?module=97&type=1",
    "title": "Documentation - Shopee Open Platform"
  },
  {
    "name": "get_income_overview",
    "url": "https://open.shopee.com/documents/v2/v2.payment.get_income_overview?module=97&type=1",
    "title": "Documentation - Shopee Open Platform"
  },
  {
    "name": "get_income_report",
    "url": "https://open.shopee.com/documents/v2/v2.payment.get_income_report?module=97&type=1",
    "title": "Documentation - Shopee Open Platform"
  },
  {
    "name": "get_income_statement",
    "url": "https://open.shopee.com/documents/v2/v2.payment.get_income_statement?module=97&type=1",
    "title": "Documentation - Shopee Open Platform"
  },
  {
    "name": "get_item_installment_status",
    "url": "https://open.shopee.com/documents/v2/v2.payment.get_item_installment_status?module=97&type=1",
    "title": "Documentation - Shopee Open Platform"
  },
  {
    "name": "get_payment_method_list",
    "url": "https://open.shopee.com/documents/v2/v2.payment.get_payment_method_list?module=97&type=1",
    "title": "Documentation - Shopee Open Platform"
  },
  {
    "name": "get_payout_detail",
    "url": "https://open.shopee.com/documents/v2/v2.payment.get_payout_detail?module=97&type=1",
    "title": "Documentation - Shopee Open Platform"
  },
  {
    "name": "get_payout_info",
    "url": "https://open.shopee.com/documents/v2/v2.payment.get_payout_info?module=97&type=1",
    "title": "Documentation - Shopee Open Platform"
  },
  {
    "name": "get_shop_installment_status",
    "url": "https://open.shopee.com/documents/v2/v2.payment.get_shop_installment_status?module=97&type=1",
    "title": "Documentation - Shopee Open Platform"
  },
  {
    "name": "get_wallet_transaction_list",
    "url": "https://open.shopee.com/documents/v2/v2.payment.get_wallet_transaction_list?module=97&type=1",
    "title": "Documentation - Shopee Open Platform"
  }
]